openpond/__init__.py
openpond/sdk.py
openpond/types.py
openpond_sdk-0.1.0.dist-info/METADATA
openpond_sdk-0.1.0.dist-info/WHEEL
openpond_sdk-0.1.0.dist-info/top_level.txt
openpond_sdk-0.1.0.dist-info/RECORD
