Metadata-Version: 2.2
Name: openpond-sdk
Version: 0.1.0
Summary: A Python SDK for interacting with the OpenPond P2P network
Home-page: https://github.com/duckailabs/openpond-sdk
Author: OpenPond
Author-email: sam@align.network
Classifier: Programming Language :: Python :: 3
Classifier: License :: OSI Approved :: MIT License
Classifier: Operating System :: OS Independent
Requires-Python: >=3.7
Requires-Dist: requests>=2.31.0
Requires-Dist: typing-extensions>=4.7.1
Dynamic: author
Dynamic: author-email
Dynamic: classifier
Dynamic: description
Dynamic: description-content-type
Dynamic: home-page
Dynamic: requires-dist
Dynamic: requires-python
Dynamic: summary
